pqam_dparamhu2021/HEA_pred.R
pqam_dparamhu2021/LICENSE
pqam_dparamhu2021/__init__.py
pqam_dparamhu2021/descriptors_gen_dev_predict_gsf.R
pqam_dparamhu2021/descriptors_gen_dev_predict_surf.R
pqam_dparamhu2021/elemental_features.csv
pqam_dparamhu2021/features_gsf.Rdata
pqam_dparamhu2021/features_surf.Rdata
pqam_dparamhu2021/gbm-locfit.R
pqam_dparamhu2021/locfit_3_var_all.Rdata
pqam_dparamhu2021/locfit_surf_2_var_all.Rdata
pqam_dparamhu2021/model.py
pqam_dparamhu2021/outputDefinition.json
pqam_dparamhu2021-0.1.13.dist-info/METADATA
pqam_dparamhu2021-0.1.13.dist-info/WHEEL
pqam_dparamhu2021-0.1.13.dist-info/top_level.txt
pqam_dparamhu2021-0.1.13.dist-info/RECORD
