Metadata-Version: 2.1
Name: pqam_dparamhu2021
Version: 0.1.13
Summary: PyQAlloy-compatible Model for D Parameter prediction based on Hu 2021 (10.1016/j.actamat.2021.116800)
Author-email: Adam Krajewski <ak@psu.edu>
Project-URL: Homepage, https://github.com/amkrajewski/pqam-dparamhu2021
Project-URL: Bug Tracker, https://github.com/amkrajewski/pqam-dparamhu2021/issues
Classifier: Programming Language :: Python :: 3
Classifier: Programming Language :: Python :: 3.9
Classifier: Programming Language :: Python :: 3.10
Classifier: Programming Language :: Python :: 3.11
Classifier: Programming Language :: Python :: 3.12
Classifier: Development Status :: 4 - Beta
Classifier: Intended Audience :: Science/Research
Classifier: License :: OSI Approved :: MIT License
Classifier: Operating System :: OS Independent
Classifier: Topic :: Scientific/Engineering
Classifier: Topic :: Scientific/Engineering :: Artificial Intelligence
Classifier: Topic :: Scientific/Engineering :: Chemistry
Classifier: Topic :: Scientific/Engineering :: Physics
Requires-Python: >=3.9
Requires-Dist: pymatgen >=2024.2.20
Requires-Dist: numpy <2.0.0,>=1.25.0
Requires-Dist: rpy2 >=3.5.14
